Metadata-Version: 1.2
Name: visyerres-sgdf
Version: 0.1
Summary: interactions with SGDF digital resources for Vis'Yerres
Home-page: https://sgdf.visyerres.org/
Author: Thomas Touhey
Author-email: thomas@touhey.fr
License: Proprietary
Platform: UNKNOWN
Requires-Python: >=3.6
